{"file":"login.vue.mjs","mappings":";;;;AAAA,SAAA,eAAA,MAAA,OAAA,SAGY;;;;;;;;;;","names":[],"sources":["../../../../pages/login.vue"],"sourcesContent":["<template>\r\n  <!-- component -->\r\n  <!-- This is an example component -->\r\n  <div class=\"font-sans\">\r\n    <div\r\n      class=\"relative min-h-screen flex flex-col sm:justify-center items-center bg-gray-100\"\r\n    >\r\n      <div class=\"relative sm:max-w-sm w-full\">\r\n        <div\r\n          class=\"card bg-blue-400 shadow-lg w-full h-full rounded-3xl absolute transform -rotate-6\"\r\n        ></div>\r\n        <div\r\n          class=\"card bg-red-400 shadow-lg w-full h-full rounded-3xl absolute transform rotate-6\"\r\n        ></div>\r\n        <div\r\n          class=\"relative w-full rounded-3xl px-6 py-4 bg-gray-100 shadow-md\"\r\n        >\r\n          <label\r\n            for=\"\"\r\n            class=\"block mt-2 text-lg text-gray-700 text-center font-semibold\"\r\n          >\r\n            Login\r\n          </label>\r\n          <form method=\"#\" action=\"#\" class=\"mt-10\">\r\n            <div>\r\n              <input\r\n                type=\"email\"\r\n                placeholder=\"Username or Email\"\r\n                class=\"mt-1 px-4 block w-full border-none bg-gray-100 h-11 rounded-xl shadow-lg hover:bg-blue-100 focus:bg-blue-100 focus:ring-0\"\r\n              />\r\n            </div>\r\n\r\n            <div class=\"mt-7\">\r\n              <input\r\n                type=\"password\"\r\n                placeholder=\"Password\"\r\n                class=\"mt-1 px-4 block w-full border-none bg-gray-100 h-11 rounded-xl shadow-lg hover:bg-blue-100 focus:bg-blue-100 focus:ring-0\"\r\n              />\r\n            </div>\r\n\r\n            <div class=\"mt-7 flex\">\r\n              <label\r\n                for=\"remember_me\"\r\n                class=\"inline-flex items-center w-full cursor-pointer\"\r\n              >\r\n                <input\r\n                  id=\"remember_me\"\r\n                  type=\"checkbox\"\r\n                  class=\"rounded border-gray-300 text-indigo-600 shadow-sm focus:border-indigo-300 focus:ring focus:ring-indigo-200 focus:ring-opacity-50\"\r\n                  name=\"remember\"\r\n                />\r\n                <span class=\"ml-2 text-sm text-gray-600\"> Remember </span>\r\n              </label>\r\n\r\n              <div class=\"w-full text-right\">\r\n                <a\r\n                  class=\"underline text-sm text-gray-600 hover:text-gray-900\"\r\n                  href=\"#\"\r\n                >\r\n                  Forget your password?\r\n                </a>\r\n              </div>\r\n            </div>\r\n\r\n            <div class=\"mt-7\">\r\n              <button\r\n                class=\"bg-blue-500 w-full py-3 rounded-xl text-white shadow-xl hover:shadow-inner focus:outline-none transition duration-500 ease-in-out transform hover:-translate-x hover:scale-105\"\r\n              >\r\n                Login\r\n              </button>\r\n            </div>\r\n\r\n            <div class=\"flex mt-7 items-center text-center\">\r\n              <hr class=\"border-gray-300 border-1 w-full rounded-md\" />\r\n              <label class=\"block font-medium text-sm text-gray-600 w-full\">\r\n                Access on\r\n              </label>\r\n              <hr class=\"border-gray-300 border-1 w-full rounded-md\" />\r\n            </div>\r\n\r\n            <div class=\"flex mt-7 justify-center w-full\">\r\n              <button\r\n                class=\"mr-5 bg-blue-500 border-none px-4 py-2 rounded-xl cursor-pointer text-white shadow-xl hover:shadow-inner transition duration-500 ease-in-out transform hover:-translate-x hover:scale-105\"\r\n              >\r\n                Facebook\r\n              </button>\r\n\r\n              <button\r\n                class=\"bg-red-500 border-none px-4 py-2 rounded-xl cursor-pointer text-white shadow-xl hover:shadow-inner transition duration-500 ease-in-out transform hover:-translate-x hover:scale-105\"\r\n              >\r\n                Google\r\n              </button>\r\n            </div>\r\n\r\n            <div class=\"mt-7\">\r\n              <div class=\"flex justify-center items-center\">\r\n                <label class=\"mr-2\">Have not account?</label>\r\n                <a\r\n                  href=\"#\"\r\n                  class=\"text-blue-500 transition duration-500 ease-in-out transform hover:-translate-x hover:scale-105\"\r\n                >\r\n                  Sign up\r\n                </a>\r\n              </div>\r\n            </div>\r\n          </form>\r\n        </div>\r\n      </div>\r\n    </div>\r\n  </div>\r\n</template>\r\n\r\n<script setup>\r\n</script>\r\n\r\n<style lang=\"scss\" scoped></style>\r\n"],"version":3}